README.md
setup.py
rlmodels.egg-info/PKG-INFO
rlmodels.egg-info/SOURCES.txt
rlmodels.egg-info/dependency_links.txt
rlmodels.egg-info/requires.txt
rlmodels.egg-info/top_level.txt
rlmodels/models/AC.py
rlmodels/models/CMAES.py
rlmodels/models/DDPG.py
rlmodels/models/DQN.py
rlmodels/models/__init__.py
rlmodels/models/grad_utils.py
rlmodels/nets/ContinuousPolicy.py
rlmodels/nets/DiscretePolicy.py
rlmodels/nets/FullyConnected.py
rlmodels/nets/__init__.py