Metadata-Version: 2.1
Name: rlmodels
Version: 1.1.0
Summary: Implementation of some popular reinforcement learning models
Home-page: https://github.com/nestorsag/rlmodels
Author: Nestor Sanchez
Author-email: nestor.sag@gmail.com
License: MIT
Download-URL: https://github.com/nestorSag/rlmodels/archive/1.0.8.tar.gz
Platform: UNKNOWN
Classifier: Programming Language :: Python :: 3
Classifier: License :: OSI Approved :: MIT License
Classifier: Operating System :: OS Independent
